ensuechaos/__init__.py
ensuechaos/ensuechaos.py
ensuechaos-2.2.dist-info/LICENSE
ensuechaos-2.2.dist-info/METADATA
ensuechaos-2.2.dist-info/WHEEL
ensuechaos-2.2.dist-info/entry_points.txt
ensuechaos-2.2.dist-info/top_level.txt
ensuechaos-2.2.dist-info/RECORD
