Metadata-Version: 2.1
Name: ensuechaos
Version: 2.2
Summary: Just a useless tool that makes your screen go crazy (FLASH WARNING)
Author-email: Ryan Sakurai <ryansakurai03@gmail.com>
License: MIT License
Project-URL: repository, https://github.com/ryansakurai/ensuechaos.git
Classifier: Programming Language :: Python :: 3
Classifier: License :: OSI Approved :: MIT License
Classifier: Operating System :: OS Independent
License-File: LICENSE
Requires-Dist: pyautogui
Requires-Dist: colorama
